[
  {
    "id": "yoichi",
    "name": "余市港",
    "prefecture": "北海道",
    "area": "北海道後志",
    "lat": 43.195,
    "lon": 140.784,
    "jmaCode": "016000",
    "jmaArea": "後志地方",
    "tidePort": "yoichi",
    "types": [
      "堤防",
      "港"
    ],
    "tidePc": 1,
    "tideHc": null
  },
  {
    "id": "otaru",
    "name": "小樽港",
    "prefecture": "北海道",
    "area": "北海道石狩",
    "lat": 43.19,
    "lon": 140.995,
    "jmaCode": "016000",
    "jmaArea": "石狩・空知・後志地方",
    "tidePort": "otaru",
    "types": [
      "堤防",
      "港"
    ],
    "tidePc": 1,
    "tideHc": null
  },
  {
    "id": "kushiro",
    "name": "釧路港",
    "prefecture": "北海道",
    "area": "北海道釧路",
    "lat": 42.979,
    "lon": 144.382,
    "jmaCode": "014000",
    "jmaArea": "釧路地方",
    "tidePort": "kushiro",
    "types": [
      "堤防",
      "港"
    ],
    "tidePc": 1,
    "tideHc": null
  },
  {
    "id": "hakodate",
    "name": "函館港",
    "prefecture": "北海道",
    "area": "北海道渡島",
    "lat": 41.773,
    "lon": 140.726,
    "jmaCode": "017000",
    "jmaArea": "渡島地方",
    "tidePort": "hakodate",
    "types": [
      "堤防",
      "港"
    ],
    "tidePc": 1,
    "tideHc": null
  },
  {
    "id": "tomakomai",
    "name": "苫小牧港",
    "prefecture": "北海道",
    "area": "北海道胆振",
    "lat": 42.633,
    "lon": 141.616,
    "jmaCode": "015000",
    "jmaArea": "胆振地方",
    "tidePort": "tomakomai",
    "types": [
      "堤防",
      "港"
    ],
    "tidePc": 1,
    "tideHc": null
  },
  {
    "id": "hachinohe",
    "name": "八戸港",
    "prefecture": "青森",
    "area": "青森東部",
    "lat": 40.533,
    "lon": 141.528,
    "jmaCode": "020000",
    "jmaArea": "三八地方",
    "tidePort": "hachinohe",
    "types": [
      "堤防",
      "港"
    ],
    "tidePc": 2,
    "tideHc": null
  },
  {
    "id": "aomori",
    "name": "青森港",
    "prefecture": "青森",
    "area": "青森中部",
    "lat": 40.82,
    "lon": 140.741,
    "jmaCode": "020000",
    "jmaArea": "津軽地方",
    "tidePort": "aomori",
    "types": [
      "堤防",
      "港"
    ],
    "tidePc": 2,
    "tideHc": null
  },
  {
    "id": "miyako",
    "name": "宮古港",
    "prefecture": "岩手",
    "area": "岩手沿岸北部",
    "lat": 39.641,
    "lon": 141.952,
    "jmaCode": "030000",
    "jmaArea": "沿岸北部",
    "tidePort": "miyako",
    "types": [
      "堤防",
      "港",
      "磯"
    ],
    "tidePc": 3,
    "tideHc": null
  },
  {
    "id": "kamaishi",
    "name": "釜石港",
    "prefecture": "岩手",
    "area": "岩手沿岸南部",
    "lat": 39.275,
    "lon": 141.886,
    "jmaCode": "030000",
    "jmaArea": "沿岸南部",
    "tidePort": "kamaishi",
    "types": [
      "堤防",
      "港"
    ],
    "tidePc": 3,
    "tideHc": null
  },
  {
    "id": "kesennuma",
    "name": "気仙沼港",
    "prefecture": "宮城",
    "area": "宮城北部",
    "lat": 38.908,
    "lon": 141.574,
    "jmaCode": "040000",
    "jmaArea": "北部",
    "tidePort": "kesennuma",
    "types": [
      "堤防",
      "港"
    ],
    "tidePc": 4,
    "tideHc": null
  },
  {
    "id": "shiogama",
    "name": "塩竈港",
    "prefecture": "宮城",
    "area": "宮城中部",
    "lat": 38.316,
    "lon": 141.021,
    "jmaCode": "040000",
    "jmaArea": "中部",
    "tidePort": "shiogama",
    "types": [
      "堤防",
      "港"
    ],
    "tidePc": 4,
    "tideHc": null
  },
  {
    "id": "ishinomaki",
    "name": "石巻港",
    "prefecture": "宮城",
    "area": "宮城北部",
    "lat": 38.432,
    "lon": 141.303,
    "jmaCode": "040000",
    "jmaArea": "北部",
    "tidePort": "ishinomaki",
    "types": [
      "堤防",
      "港"
    ],
    "tidePc": 4,
    "tideHc": null
  },
  {
    "id": "sakata",
    "name": "酒田港",
    "prefecture": "山形",
    "area": "山形庄内",
    "lat": 38.913,
    "lon": 139.836,
    "jmaCode": "060000",
    "jmaArea": "庄内地方",
    "tidePort": "sakata",
    "types": [
      "堤防",
      "港"
    ],
    "tidePc": 6,
    "tideHc": null
  },
  {
    "id": "onahama",
    "name": "小名浜港",
    "prefecture": "福島",
    "area": "福島浜通り",
    "lat": 36.933,
    "lon": 140.896,
    "jmaCode": "070000",
    "jmaArea": "浜通り",
    "tidePort": "onahama",
    "types": [
      "堤防",
      "港"
    ],
    "tidePc": 7,
    "tideHc": null
  },
  {
    "id": "oarai",
    "name": "大洗港",
    "prefecture": "茨城",
    "area": "茨城南部",
    "lat": 36.313,
    "lon": 140.577,
    "jmaCode": "080000",
    "jmaArea": "南部",
    "tidePort": "oarai",
    "types": [
      "堤防",
      "港",
      "磯"
    ],
    "tidePc": 8,
    "tideHc": null
  },
  {
    "id": "nakaminato",
    "name": "那珂湊港",
    "prefecture": "茨城",
    "area": "茨城北部",
    "lat": 36.335,
    "lon": 140.592,
    "jmaCode": "080000",
    "jmaArea": "北部",
    "tidePort": "nakaminato",
    "types": [
      "堤防",
      "港"
    ],
    "tidePc": 8,
    "tideHc": null
  },
  {
    "id": "choshi",
    "name": "銚子港",
    "prefecture": "千葉",
    "area": "千葉北東部",
    "lat": 35.736,
    "lon": 140.828,
    "jmaCode": "120000",
    "jmaArea": "北東部",
    "tidePort": "choshi",
    "types": [
      "堤防",
      "港",
      "磯"
    ],
    "tidePc": 12,
    "tideHc": null
  },
  {
    "id": "tateyama",
    "name": "館山港",
    "prefecture": "千葉",
    "area": "千葉南部",
    "lat": 34.995,
    "lon": 139.869,
    "jmaCode": "120000",
    "jmaArea": "南部",
    "tidePort": "tateyama",
    "types": [
      "堤防",
      "港",
      "磯"
    ],
    "tidePc": 12,
    "tideHc": null
  },
  {
    "id": "katsuura",
    "name": "勝浦港",
    "prefecture": "千葉",
    "area": "千葉東部",
    "lat": 35.154,
    "lon": 140.317,
    "jmaCode": "120000",
    "jmaArea": "東部",
    "tidePort": "katsuura",
    "types": [
      "堤防",
      "港",
      "磯"
    ],
    "tidePc": 12,
    "tideHc": null
  },
  {
    "id": "miura",
    "name": "三浦半島",
    "prefecture": "神奈川",
    "area": "神奈川南部",
    "lat": 35.133,
    "lon": 139.617,
    "jmaCode": "140000",
    "jmaArea": "東部",
    "tidePort": "yokohama",
    "types": [
      "磯",
      "堤防"
    ],
    "tidePc": 14,
    "tideHc": null
  },
  {
    "id": "manazuru",
    "name": "真鶴港",
    "prefecture": "神奈川",
    "area": "神奈川西部",
    "lat": 35.157,
    "lon": 139.139,
    "jmaCode": "140000",
    "jmaArea": "西部",
    "tidePort": "manazuru",
    "types": [
      "磯",
      "堤防"
    ],
    "tidePc": 14,
    "tideHc": null
  },
  {
    "id": "ito",
    "name": "伊東港",
    "prefecture": "静岡",
    "area": "静岡伊豆",
    "lat": 34.966,
    "lon": 139.099,
    "jmaCode": "220000",
    "jmaArea": "伊豆",
    "tidePort": "ito",
    "types": [
      "堤防",
      "磯"
    ],
    "tidePc": 22,
    "tideHc": null
  },
  {
    "id": "shimoda",
    "name": "下田港",
    "prefecture": "静岡",
    "area": "静岡伊豆南部",
    "lat": 34.679,
    "lon": 138.947,
    "jmaCode": "220000",
    "jmaArea": "伊豆",
    "tidePort": "shimoda",
    "types": [
      "堤防",
      "磯"
    ],
    "tidePc": 22,
    "tideHc": null
  },
  {
    "id": "omaezaki",
    "name": "御前崎港",
    "prefecture": "静岡",
    "area": "静岡西部",
    "lat": 34.601,
    "lon": 138.215,
    "jmaCode": "220000",
    "jmaArea": "西部",
    "tidePort": "omaezaki",
    "types": [
      "堤防",
      "磯"
    ],
    "tidePc": 22,
    "tideHc": null
  },
  {
    "id": "irago",
    "name": "伊良湖",
    "prefecture": "愛知",
    "area": "愛知渥美",
    "lat": 34.574,
    "lon": 137.024,
    "jmaCode": "230000",
    "jmaArea": "西部",
    "tidePort": "irago",
    "types": [
      "磯",
      "堤防"
    ],
    "tidePc": 23,
    "tideHc": null
  },
  {
    "id": "gamagori",
    "name": "蒲郡",
    "prefecture": "愛知",
    "area": "愛知東部",
    "lat": 34.826,
    "lon": 137.217,
    "jmaCode": "230000",
    "jmaArea": "東部",
    "tidePort": "gamagori",
    "types": [
      "堤防",
      "沖堤"
    ],
    "tidePc": 23,
    "tideHc": null
  },
  {
    "id": "minami_chita",
    "name": "南知多",
    "prefecture": "愛知",
    "area": "愛知知多",
    "lat": 34.717,
    "lon": 136.883,
    "jmaCode": "230000",
    "jmaArea": "西部",
    "tidePort": "nagoya",
    "types": [
      "堤防",
      "磯"
    ],
    "tidePc": 23,
    "tideHc": null
  },
  {
    "id": "owase",
    "name": "尾鷲港",
    "prefecture": "三重",
    "area": "三重南部",
    "lat": 34.072,
    "lon": 136.191,
    "jmaCode": "240000",
    "jmaArea": "南部",
    "tidePort": "owase",
    "types": [
      "渡船",
      "磯",
      "堤防"
    ],
    "tidePc": 24,
    "tideHc": null
  },
  {
    "id": "shima",
    "name": "志摩・英虞湾",
    "prefecture": "三重",
    "area": "三重中部",
    "lat": 34.316,
    "lon": 136.829,
    "jmaCode": "240000",
    "jmaArea": "中部",
    "tidePort": "shima",
    "types": [
      "堤防",
      "磯"
    ],
    "tidePc": 24,
    "tideHc": null
  },
  {
    "id": "kushimoto",
    "name": "串本・大島",
    "prefecture": "和歌山",
    "area": "和歌山南部",
    "lat": 33.477,
    "lon": 135.856,
    "jmaCode": "300000",
    "jmaArea": "南部",
    "tidePort": "kushimoto",
    "types": [
      "渡船",
      "磯"
    ],
    "tidePc": 30,
    "tideHc": null
  },
  {
    "id": "kada",
    "name": "加太",
    "prefecture": "和歌山",
    "area": "和歌山北部",
    "lat": 34.15,
    "lon": 135.204,
    "jmaCode": "300000",
    "jmaArea": "北部",
    "tidePort": "kada",
    "types": [
      "渡船",
      "堤防"
    ],
    "tidePc": 30,
    "tideHc": null
  },
  {
    "id": "yura",
    "name": "由良",
    "prefecture": "和歌山",
    "area": "和歌山中部",
    "lat": 33.96,
    "lon": 135.1,
    "jmaCode": "300000",
    "jmaArea": "南部",
    "tidePort": "yura",
    "types": [
      "渡船",
      "磯"
    ],
    "tidePc": 30,
    "tideHc": null
  },
  {
    "id": "susami",
    "name": "すさみ",
    "prefecture": "和歌山",
    "area": "和歌山南部",
    "lat": 33.543,
    "lon": 135.499,
    "jmaCode": "300000",
    "jmaArea": "南部",
    "tidePort": "kushimoto",
    "types": [
      "磯",
      "堤防"
    ],
    "tidePc": 30,
    "tideHc": null
  },
  {
    "id": "izumisano",
    "name": "泉佐野",
    "prefecture": "大阪",
    "area": "大阪南部",
    "lat": 34.4,
    "lon": 135.43,
    "jmaCode": "270000",
    "jmaArea": "南部",
    "tidePort": "izumisano",
    "types": [
      "堤防",
      "沖堤"
    ],
    "tidePc": 27,
    "tideHc": null
  },
  {
    "id": "sakai",
    "name": "堺・浜寺",
    "prefecture": "大阪",
    "area": "大阪湾岸",
    "lat": 34.56,
    "lon": 135.437,
    "jmaCode": "270000",
    "jmaArea": "北部",
    "tidePort": "osaka",
    "types": [
      "堤防",
      "沖堤"
    ],
    "tidePc": 27,
    "tideHc": null
  },
  {
    "id": "maiko",
    "name": "明石・舞子",
    "prefecture": "兵庫",
    "area": "兵庫東部",
    "lat": 34.637,
    "lon": 134.988,
    "jmaCode": "280000",
    "jmaArea": "南部東",
    "tidePort": "akashi",
    "types": [
      "堤防",
      "沖堤"
    ],
    "tidePc": 28,
    "tideHc": null
  },
  {
    "id": "awaji",
    "name": "淡路島・由良",
    "prefecture": "兵庫",
    "area": "淡路島",
    "lat": 34.044,
    "lon": 134.897,
    "jmaCode": "280000",
    "jmaArea": "南部西",
    "tidePort": "awaji",
    "types": [
      "渡船",
      "磯",
      "堤防"
    ],
    "tidePc": 28,
    "tideHc": null
  },
  {
    "id": "kii_mihara",
    "name": "紀伊御坊",
    "prefecture": "和歌山",
    "area": "和歌山中部",
    "lat": 33.884,
    "lon": 135.166,
    "jmaCode": "300000",
    "jmaArea": "南部",
    "tidePort": "mihara",
    "types": [
      "堤防",
      "磯"
    ],
    "tidePc": 30,
    "tideHc": null
  },
  {
    "id": "amagasaki",
    "name": "尼崎・武庫川",
    "prefecture": "兵庫",
    "area": "大阪湾岸",
    "lat": 34.701,
    "lon": 135.395,
    "jmaCode": "280000",
    "jmaArea": "南部東",
    "tidePort": "osaka",
    "types": [
      "堤防",
      "河口"
    ],
    "tidePc": 28,
    "tideHc": null
  },
  {
    "id": "himeji",
    "name": "姫路・家島",
    "prefecture": "兵庫",
    "area": "兵庫西部",
    "lat": 34.684,
    "lon": 134.603,
    "jmaCode": "280000",
    "jmaArea": "南部西",
    "tidePort": "himeji",
    "types": [
      "渡船",
      "磯",
      "堤防"
    ],
    "tidePc": 28,
    "tideHc": null
  },
  {
    "id": "tottori",
    "name": "鳥取港",
    "prefecture": "鳥取",
    "area": "鳥取中部",
    "lat": 35.503,
    "lon": 134.228,
    "jmaCode": "310000",
    "jmaArea": "中部",
    "tidePort": "tottori",
    "types": [
      "堤防",
      "港"
    ],
    "tidePc": 31,
    "tideHc": null
  },
  {
    "id": "sakaiminato",
    "name": "境港",
    "prefecture": "鳥取",
    "area": "鳥取西部",
    "lat": 35.547,
    "lon": 133.229,
    "jmaCode": "310000",
    "jmaArea": "西部",
    "tidePort": "sakaiminato",
    "types": [
      "堤防",
      "港"
    ],
    "tidePc": 31,
    "tideHc": null
  },
  {
    "id": "hamada",
    "name": "浜田港",
    "prefecture": "島根",
    "area": "島根西部",
    "lat": 34.898,
    "lon": 132.065,
    "jmaCode": "320000",
    "jmaArea": "西部",
    "tidePort": "hamada",
    "types": [
      "堤防",
      "磯"
    ],
    "tidePc": 32,
    "tideHc": null
  },
  {
    "id": "oki",
    "name": "隠岐島",
    "prefecture": "島根",
    "area": "隠岐",
    "lat": 36.188,
    "lon": 133.325,
    "jmaCode": "320000",
    "jmaArea": "隠岐",
    "tidePort": "oki",
    "types": [
      "磯",
      "堤防"
    ],
    "tidePc": 32,
    "tideHc": null
  },
  {
    "id": "kasaoka",
    "name": "笠岡諸島",
    "prefecture": "岡山",
    "area": "岡山西部",
    "lat": 34.506,
    "lon": 133.514,
    "jmaCode": "330000",
    "jmaArea": "南部",
    "tidePort": "kasaoka",
    "types": [
      "渡船",
      "磯"
    ],
    "tidePc": 33,
    "tideHc": null
  },
  {
    "id": "onomichi",
    "name": "尾道・因島",
    "prefecture": "広島",
    "area": "広島東部",
    "lat": 34.404,
    "lon": 133.197,
    "jmaCode": "340000",
    "jmaArea": "東部",
    "tidePort": "onomichi",
    "types": [
      "堤防",
      "磯"
    ],
    "tidePc": 34,
    "tideHc": null
  },
  {
    "id": "hiroshima",
    "name": "広島湾",
    "prefecture": "広島",
    "area": "広島中部",
    "lat": 34.356,
    "lon": 132.317,
    "jmaCode": "340000",
    "jmaArea": "西部",
    "tidePort": "hiroshima",
    "types": [
      "堤防",
      "沖堤"
    ],
    "tidePc": 34,
    "tideHc": null
  },
  {
    "id": "oshima",
    "name": "大島・周防大島",
    "prefecture": "山口",
    "area": "山口東部",
    "lat": 33.916,
    "lon": 132.169,
    "jmaCode": "350000",
    "jmaArea": "東部",
    "tidePort": "oshima",
    "types": [
      "渡船",
      "磯"
    ],
    "tidePc": 35,
    "tideHc": null
  },
  {
    "id": "shimonoseki",
    "name": "下関・響灘",
    "prefecture": "山口",
    "area": "山口西部",
    "lat": 33.952,
    "lon": 130.921,
    "jmaCode": "350000",
    "jmaArea": "西部",
    "tidePort": "shimonoseki",
    "types": [
      "堤防",
      "磯"
    ],
    "tidePc": 35,
    "tideHc": null
  },
  {
    "id": "tokushima",
    "name": "徳島・鳴門",
    "prefecture": "徳島",
    "area": "徳島北部",
    "lat": 34.066,
    "lon": 134.589,
    "jmaCode": "360000",
    "jmaArea": "北部",
    "tidePort": "tokushima",
    "types": [
      "堤防",
      "磯"
    ],
    "tidePc": 36,
    "tideHc": null
  },
  {
    "id": "hiwasa",
    "name": "日和佐",
    "prefecture": "徳島",
    "area": "徳島南部",
    "lat": 33.732,
    "lon": 134.53,
    "jmaCode": "360000",
    "jmaArea": "南部",
    "tidePort": "hiwasa",
    "types": [
      "磯",
      "堤防"
    ],
    "tidePc": 36,
    "tideHc": null
  },
  {
    "id": "takamatsu",
    "name": "高松港",
    "prefecture": "香川",
    "area": "香川北部",
    "lat": 34.346,
    "lon": 134.047,
    "jmaCode": "370000",
    "jmaArea": "中部",
    "tidePort": "takamatsu",
    "types": [
      "堤防",
      "沖堤"
    ],
    "tidePc": 37,
    "tideHc": null
  },
  {
    "id": "uwajima",
    "name": "宇和島",
    "prefecture": "愛媛",
    "area": "愛媛南部",
    "lat": 33.224,
    "lon": 132.56,
    "jmaCode": "380000",
    "jmaArea": "南予",
    "tidePort": "uwajima",
    "types": [
      "磯",
      "堤防"
    ],
    "tidePc": 38,
    "tideHc": null
  },
  {
    "id": "matsuyama",
    "name": "松山・興居島",
    "prefecture": "愛媛",
    "area": "愛媛中部",
    "lat": 33.847,
    "lon": 132.758,
    "jmaCode": "380000",
    "jmaArea": "中予",
    "tidePort": "matsuyama",
    "types": [
      "渡船",
      "磯"
    ],
    "tidePc": 38,
    "tideHc": null
  },
  {
    "id": "kochi",
    "name": "高知港",
    "prefecture": "高知",
    "area": "高知中部",
    "lat": 33.561,
    "lon": 133.531,
    "jmaCode": "390000",
    "jmaArea": "中部",
    "tidePort": "kochi",
    "types": [
      "堤防",
      "沖堤"
    ],
    "tidePc": 39,
    "tideHc": null
  },
  {
    "id": "ashizuri",
    "name": "足摺岬",
    "prefecture": "高知",
    "area": "高知西部",
    "lat": 32.727,
    "lon": 132.982,
    "jmaCode": "390000",
    "jmaArea": "西部",
    "tidePort": "ashizuri",
    "types": [
      "磯"
    ],
    "tidePc": 39,
    "tideHc": null
  },
  {
    "id": "muroto",
    "name": "室戸岬",
    "prefecture": "高知",
    "area": "高知東部",
    "lat": 33.293,
    "lon": 134.178,
    "jmaCode": "390000",
    "jmaArea": "東部",
    "tidePort": "muroto",
    "types": [
      "磯",
      "堤防"
    ],
    "tidePc": 39,
    "tideHc": null
  },
  {
    "id": "fukuoka",
    "name": "博多・志賀島",
    "prefecture": "福岡",
    "area": "福岡北部",
    "lat": 33.638,
    "lon": 130.421,
    "jmaCode": "400000",
    "jmaArea": "福岡・筑後",
    "tidePort": "fukuoka",
    "types": [
      "堤防",
      "磯",
      "沖堤"
    ],
    "tidePc": 40,
    "tideHc": null
  },
  {
    "id": "kitakyushu",
    "name": "北九州・若松",
    "prefecture": "福岡",
    "area": "福岡北部",
    "lat": 33.879,
    "lon": 130.825,
    "jmaCode": "400000",
    "jmaArea": "北九州・豊前",
    "tidePort": "kitakyushu",
    "types": [
      "堤防",
      "港"
    ],
    "tidePc": 40,
    "tideHc": null
  },
  {
    "id": "karatsu",
    "name": "唐津",
    "prefecture": "佐賀",
    "area": "佐賀北部",
    "lat": 33.449,
    "lon": 129.967,
    "jmaCode": "410000",
    "jmaArea": "北部",
    "tidePort": "karatsu",
    "types": [
      "堤防",
      "磯",
      "港"
    ],
    "tidePc": 41,
    "tideHc": null
  },
  {
    "id": "nagasaki",
    "name": "長崎港",
    "prefecture": "長崎",
    "area": "長崎中部",
    "lat": 32.737,
    "lon": 129.867,
    "jmaCode": "420000",
    "jmaArea": "長崎・島原",
    "tidePort": "nagasaki",
    "types": [
      "堤防",
      "磯"
    ],
    "tidePc": 42,
    "tideHc": null
  },
  {
    "id": "goto",
    "name": "五島列島",
    "prefecture": "長崎",
    "area": "五島",
    "lat": 32.694,
    "lon": 128.831,
    "jmaCode": "420000",
    "jmaArea": "五島",
    "tidePort": "goto",
    "types": [
      "磯",
      "渡船"
    ],
    "tidePc": 42,
    "tideHc": null
  },
  {
    "id": "tsushima",
    "name": "対馬",
    "prefecture": "長崎",
    "area": "対馬",
    "lat": 34.205,
    "lon": 129.291,
    "jmaCode": "420000",
    "jmaArea": "対馬・壱岐",
    "tidePort": "tsushima",
    "types": [
      "磯",
      "堤防"
    ],
    "tidePc": 42,
    "tideHc": null
  },
  {
    "id": "amakusa",
    "name": "天草",
    "prefecture": "熊本",
    "area": "熊本西部",
    "lat": 32.458,
    "lon": 130.195,
    "jmaCode": "430000",
    "jmaArea": "天草・芦北地方",
    "tidePort": "amakusa",
    "types": [
      "磯",
      "堤防"
    ],
    "tidePc": 43,
    "tideHc": null
  },
  {
    "id": "usuki",
    "name": "臼杵・佐伯",
    "prefecture": "大分",
    "area": "大分南部",
    "lat": 32.973,
    "lon": 131.802,
    "jmaCode": "440000",
    "jmaArea": "中部・南部",
    "tidePort": "saiki",
    "types": [
      "磯",
      "堤防"
    ],
    "tidePc": 44,
    "tideHc": null
  },
  {
    "id": "beppu",
    "name": "別府湾",
    "prefecture": "大分",
    "area": "大分北部",
    "lat": 33.278,
    "lon": 131.491,
    "jmaCode": "440000",
    "jmaArea": "北部",
    "tidePort": "oita",
    "types": [
      "堤防",
      "沖堤"
    ],
    "tidePc": 44,
    "tideHc": null
  },
  {
    "id": "miyazaki",
    "name": "宮崎港",
    "prefecture": "宮崎",
    "area": "宮崎中部",
    "lat": 31.916,
    "lon": 131.423,
    "jmaCode": "450000",
    "jmaArea": "宮崎・東諸県",
    "tidePort": "miyazaki",
    "types": [
      "堤防",
      "港"
    ],
    "tidePc": 45,
    "tideHc": null
  },
  {
    "id": "nichinan",
    "name": "日南・油津",
    "prefecture": "宮崎",
    "area": "宮崎南部",
    "lat": 31.594,
    "lon": 131.398,
    "jmaCode": "450000",
    "jmaArea": "日南・串間",
    "tidePort": "aburatsu",
    "types": [
      "磯",
      "堤防"
    ],
    "tidePc": 45,
    "tideHc": null
  },
  {
    "id": "makurazaki",
    "name": "枕崎",
    "prefecture": "鹿児島",
    "area": "鹿児島南薩",
    "lat": 31.272,
    "lon": 130.297,
    "jmaCode": "460000",
    "jmaArea": "薩摩地方",
    "tidePort": "makurazaki",
    "types": [
      "磯",
      "堤防"
    ],
    "tidePc": 46,
    "tideHc": null
  },
  {
    "id": "kagoshima",
    "name": "鹿児島港",
    "prefecture": "鹿児島",
    "area": "鹿児島中部",
    "lat": 31.597,
    "lon": 130.557,
    "jmaCode": "460000",
    "jmaArea": "薩摩地方",
    "tidePort": "kagoshima",
    "types": [
      "堤防",
      "港"
    ],
    "tidePc": 46,
    "tideHc": null
  },
  {
    "id": "tanegashima",
    "name": "種子島",
    "prefecture": "鹿児島",
    "area": "種子島・屋久島",
    "lat": 30.528,
    "lon": 130.959,
    "jmaCode": "460000",
    "jmaArea": "種子島・屋久島地方",
    "tidePort": "tanegashima",
    "types": [
      "磯",
      "堤防"
    ],
    "tidePc": 46,
    "tideHc": null
  },
  {
    "id": "amami",
    "name": "奄美大島",
    "prefecture": "鹿児島",
    "area": "奄美大島",
    "lat": 28.375,
    "lon": 129.491,
    "jmaCode": "460000",
    "jmaArea": "奄美地方",
    "tidePort": "amami",
    "types": [
      "磯",
      "堤防"
    ],
    "tidePc": 46,
    "tideHc": null
  },
  {
    "id": "naha",
    "name": "那覇港",
    "prefecture": "沖縄",
    "area": "沖縄本島",
    "lat": 26.213,
    "lon": 127.679,
    "jmaCode": "471000",
    "jmaArea": "沖縄本島中南部",
    "tidePort": "naha",
    "types": [
      "堤防",
      "港"
    ],
    "tidePc": 47,
    "tideHc": null
  },
  {
    "id": "nago",
    "name": "名護・本部",
    "prefecture": "沖縄",
    "area": "沖縄本島北部",
    "lat": 26.59,
    "lon": 127.977,
    "jmaCode": "471000",
    "jmaArea": "沖縄本島北部",
    "tidePort": "nago",
    "types": [
      "磯",
      "堤防"
    ],
    "tidePc": 47,
    "tideHc": null
  },
  {
    "id": "miyakojima",
    "name": "宮古島",
    "prefecture": "沖縄",
    "area": "宮古",
    "lat": 24.805,
    "lon": 125.281,
    "jmaCode": "472000",
    "jmaArea": "宮古島地方",
    "tidePort": "hirara",
    "types": [
      "磯",
      "堤防"
    ],
    "tidePc": 47,
    "tideHc": null
  },
  {
    "id": "ishigaki",
    "name": "石垣島",
    "prefecture": "沖縄",
    "area": "八重山",
    "lat": 24.337,
    "lon": 124.157,
    "jmaCode": "473000",
    "jmaArea": "八重山地方",
    "tidePort": "ishigaki",
    "types": [
      "磯",
      "堤防"
    ],
    "tidePc": 47,
    "tideHc": null
  },
  {
    "id": "niigata",
    "name": "新潟港",
    "prefecture": "新潟",
    "area": "新潟中部",
    "lat": 37.916,
    "lon": 139.037,
    "jmaCode": "150000",
    "jmaArea": "中越",
    "tidePort": "niigata",
    "types": [
      "堤防",
      "港"
    ],
    "tidePc": 15,
    "tideHc": null
  },
  {
    "id": "joetsu",
    "name": "上越・直江津",
    "prefecture": "新潟",
    "area": "新潟上越",
    "lat": 37.097,
    "lon": 138.263,
    "jmaCode": "150000",
    "jmaArea": "上越",
    "tidePort": "naoetsu",
    "types": [
      "堤防",
      "港"
    ],
    "tidePc": 15,
    "tideHc": null
  },
  {
    "id": "toyama",
    "name": "富山港",
    "prefecture": "富山",
    "area": "富山中部",
    "lat": 36.748,
    "lon": 137.196,
    "jmaCode": "160000",
    "jmaArea": "富山",
    "tidePort": "toyama",
    "types": [
      "堤防",
      "港"
    ],
    "tidePc": 16,
    "tideHc": null
  },
  {
    "id": "himi",
    "name": "氷見",
    "prefecture": "富山",
    "area": "富山西部",
    "lat": 36.851,
    "lon": 136.987,
    "jmaCode": "160000",
    "jmaArea": "富山",
    "tidePort": "himi",
    "types": [
      "堤防",
      "磯"
    ],
    "tidePc": 16,
    "tideHc": null
  },
  {
    "id": "kanazawa",
    "name": "金沢港",
    "prefecture": "石川",
    "area": "石川中部",
    "lat": 36.573,
    "lon": 136.626,
    "jmaCode": "170000",
    "jmaArea": "加賀",
    "tidePort": "kanazawa",
    "types": [
      "堤防",
      "港"
    ],
    "tidePc": 17,
    "tideHc": null
  },
  {
    "id": "noto",
    "name": "能登半島",
    "prefecture": "石川",
    "area": "石川能登",
    "lat": 37.331,
    "lon": 136.754,
    "jmaCode": "170000",
    "jmaArea": "能登",
    "tidePort": "wajima",
    "types": [
      "磯",
      "堤防"
    ],
    "tidePc": 17,
    "tideHc": null
  },
  {
    "id": "fukui",
    "name": "福井・三国",
    "prefecture": "福井",
    "area": "福井北部",
    "lat": 36.199,
    "lon": 136.077,
    "jmaCode": "180000",
    "jmaArea": "嶺北",
    "tidePort": "mikuni",
    "types": [
      "堤防",
      "磯"
    ],
    "tidePc": 18,
    "tideHc": null
  },
  {
    "id": "wakasa",
    "name": "若狭・小浜",
    "prefecture": "福井",
    "area": "福井南部",
    "lat": 35.498,
    "lon": 135.748,
    "jmaCode": "180000",
    "jmaArea": "嶺南",
    "tidePort": "obama",
    "types": [
      "磯",
      "堤防"
    ],
    "tidePc": 18,
    "tideHc": null
  },
  {
    "id": "maizuru",
    "name": "舞鶴",
    "prefecture": "京都",
    "area": "京都北部",
    "lat": 35.474,
    "lon": 135.388,
    "jmaCode": "260000",
    "jmaArea": "北部",
    "tidePort": "maizuru",
    "types": [
      "堤防",
      "磯"
    ],
    "tidePc": 26,
    "tideHc": null
  },
  {
    "id": "kyotango",
    "name": "京丹後・間人",
    "prefecture": "京都",
    "area": "京都北部",
    "lat": 35.734,
    "lon": 135.02,
    "jmaCode": "260000",
    "jmaArea": "北部",
    "tidePort": "kyotango",
    "types": [
      "磯",
      "堤防"
    ],
    "tidePc": 26,
    "tideHc": null
  },
  {
    "id": "toyooka",
    "name": "豊岡・竹野",
    "prefecture": "兵庫",
    "area": "兵庫北部",
    "lat": 35.612,
    "lon": 134.818,
    "jmaCode": "280000",
    "jmaArea": "北部",
    "tidePort": "toyooka",
    "types": [
      "磯",
      "堤防"
    ],
    "tidePc": 28,
    "tideHc": null
  },
  {
    "id": "akita",
    "name": "秋田港",
    "prefecture": "秋田",
    "area": "秋田中部",
    "lat": 39.72,
    "lon": 140.092,
    "jmaCode": "050000",
    "jmaArea": "秋田",
    "tidePort": "akita",
    "types": [
      "堤防",
      "港"
    ],
    "tidePc": 5,
    "tideHc": null
  },
  {
    "id": "oga",
    "name": "男鹿半島",
    "prefecture": "秋田",
    "area": "秋田北部",
    "lat": 39.876,
    "lon": 139.841,
    "jmaCode": "050000",
    "jmaArea": "秋田",
    "tidePort": "oga",
    "types": [
      "磯",
      "堤防"
    ],
    "tidePc": 5,
    "tideHc": null
  },
  {
    "id": "sakata_port",
    "name": "酒田港・飛島",
    "prefecture": "山形",
    "area": "山形庄内",
    "lat": 38.913,
    "lon": 139.836,
    "jmaCode": "060000",
    "jmaArea": "庄内地方",
    "tidePort": "sakata",
    "types": [
      "堤防",
      "磯",
      "渡船"
    ],
    "tidePc": 6,
    "tideHc": null
  },
  {
    "id": "iwaki",
    "name": "いわき・小名浜",
    "prefecture": "福島",
    "area": "福島浜通り",
    "lat": 36.933,
    "lon": 140.896,
    "jmaCode": "070000",
    "jmaArea": "浜通り",
    "tidePort": "onahama",
    "types": [
      "堤防",
      "磯"
    ],
    "tidePc": 7,
    "tideHc": null
  }
]